MANIFEST.in
README
setup.cfg
setup.py
Flask_Flarf.egg-info/PKG-INFO
Flask_Flarf.egg-info/SOURCES.txt
Flask_Flarf.egg-info/dependency_links.txt
Flask_Flarf.egg-info/not-zip-safe
Flask_Flarf.egg-info/requires.txt
Flask_Flarf.egg-info/top_level.txt
flask_flarf/__init__.py
flask_flarf/flarf.py
tests/test_flarf.py