Metadata-Version: 1.1
Name: Flask-Flarf
Version: 0.0.5
Summary: Flask request filtering
Home-page: https://github.com/thrisp/flarf
Author: Thrisp/Hurrata
Author-email: blueblank@gmail.com
License: MIT
Platform: any
Classifier: Development Status :: 4 - Beta
Classifier: Environment :: Web Environment
Classifier: Intended Audience :: Developers
Classifier: License :: OSI Approved :: MIT License
Classifier: Operating System :: OS Independent
Classifier: Programming Language :: Python
Classifier: Programming Language :: Python :: 3
Classifier: Topic :: Internet :: WWW/HTTP :: Dynamic Content
Classifier: Topic :: Software Development :: Libraries :: Python Modules
